{
    "family": "cows-shelter-app",
    "executionRoleArn": "arn:aws:iam::002824154008:role/cows-shelter-ecs-task-execution-role",
    "networkMode": "awsvpc",
    "containerDefinitions": [
        {
            "name": "app",
            "image": "002824154008.dkr.ecr.eu-north-1.amazonaws.com/cows-shelter-backend:latest",
            "cpu": 0,
            "portMappings": [
                {
                    "containerPort": 8080,
                    "hostPort": 8080,
                    "protocol": "tcp"
                }
            ],
            "essential": true,
            "environment": [
                {
                    "name": "MINIO_BUCKET",
                    "value": "cows-shelter"
                },
                {
                    "name": "DB_PORT",
                    "value": "5432"
                },
                {
                    "name": "GIN_MODE",
                    "value": "release"
                },
                {
                    "name": "DB_USER",
                    "value": "postgres"
                },
                {
                    "name": "AWS_SDK_LOAD_CONFIG",
                    "value": "true"
                },
                {
                    "name": "MINIO_USE_SSL",
                    "value": "true"
                },
                {
                    "name": "DB_NAME",
                    "value": "cows_shelter"
                },
                {
                    "name": "MINIO_ENDPOINT",
                    "value": "s3.eu-north-1.amazonaws.com"
                },
                {
                    "name": "AWS_REGION",
                    "value": "eu-north-1"
                },
                {
                    "name": "DB_HOST",
                    "value": "cows-shelter-db.cfcuqq86u682.eu-north-1.rds.amazonaws.com"
                },
                {
                    "name": "DB_PASSWORD",
                    "value": "OsIUxvObUVCUtIiW"
                }
            ],
            "mountPoints": [],
            "volumesFrom": [],
            "logConfiguration": {
                "logDriver": "awslogs",
                "options": {
                    "awslogs-group": "/ecs/cows-shelter-app",
                    "awslogs-region": "eu-north-1",
                    "awslogs-stream-prefix": "ecs"
                }
            }
        }
    ],
    "requiresCompatibilities": ["FARGATE"],
    "cpu": "256",
    "memory": "512",
    "volumes": []
}
